<annotation>
	<folder>images</folder>
	<filename>10813.jpg</filename>
	<path>D:\sxdx\ZDSC\waterToPuddle\upload\dataset - 副本\images\10813.jpg</path>
	<source>
		<database>Unknown</database>
	</source>
	<size>
		<width>640</width>
		<height>640</height>
		<depth>3</depth>
	</size>
	<segmented>0</segmented>
	<object>
		<name>puddle</name>
		<pose>Unspecified</pose>
		<truncated>1</truncated>
		<difficult>0</difficult>
		<bndbox>
			<xmin>10</xmin>
			<ymin>146</ymin>
			<xmax>640</xmax>
			<ymax>402</ymax>
		</bndbox>
	</object>
</annotation>
